README.md
setup.py
libpythonproVictor/__init__.py
libpythonproVictor/github_api.py
libpythonproVictor.egg-info/PKG-INFO
libpythonproVictor.egg-info/SOURCES.txt
libpythonproVictor.egg-info/dependency_links.txt
libpythonproVictor.egg-info/not-zip-safe
libpythonproVictor.egg-info/requires.txt
libpythonproVictor.egg-info/top_level.txt